qf_package/__init__.py
qf_package-0.2.dist-info/METADATA
qf_package-0.2.dist-info/WHEEL
qf_package-0.2.dist-info/top_level.txt
qf_package-0.2.dist-info/RECORD
