Metadata-Version: 2.1
Name: qf-package
Version: 0.2
Summary: Useful things for QF projects sharing
Home-page: https://github.com/quality-first/qf-package
Author: Anton Stefanovich
Author-email: anton.stefanovich@gmail.com
License: MIT
Platform: UNKNOWN
Requires-Dist: setuptools
Requires-Dist: twine
Requires-Dist: wheel
